blueno/__init__.py
blueno/auth.py
blueno/cli.py
blueno/display.py
blueno/exceptions.py
blueno/fabric.py
blueno/types.py
blueno/etl/__init__.py
blueno/etl/config.py
blueno/etl/load/__init__.py
blueno/etl/load/delta.py
blueno/etl/load/parquet.py
blueno/etl/read/__init__.py
blueno/etl/read/delta.py
blueno/etl/read/parquet.py
blueno/etl/transform/__init__.py
blueno/etl/transform/transforms.py
blueno/orchestration/__init__.py
blueno/orchestration/blueprint.py
blueno/orchestration/config.py
blueno/orchestration/job.py
blueno/orchestration/pipeline.py
blueno/orchestration/run_context.py
blueno/orchestration/task.py
blueno/utils/__init__.py
blueno/utils/delta.py
blueno/utils/merge_helpers.py
blueno/utils/misc.py
blueno/utils/string_normalization.py
blueno-0.5.0.dist-info/licenses/LICENSE
blueno-0.5.0.dist-info/METADATA
blueno-0.5.0.dist-info/WHEEL
blueno-0.5.0.dist-info/entry_points.txt
blueno-0.5.0.dist-info/top_level.txt
blueno-0.5.0.dist-info/RECORD
