Metadata-Version: 2.4
Name: blueno
Version: 0.5.0
Summary: A Python ETL library for creating declarative data pipelines.
Author: Jimmy Jensen
Project-URL: Repository, https://github.com/mrjsj/blueno
Keywords: etl,deltalake,polars,delta-rs,fabric,Microsoft,azure
Classifier: Programming Language :: Python :: 3
Classifier: Programming Language :: Python :: 3.10
Classifier: Programming Language :: Python :: 3.11
Classifier: Programming Language :: Python :: 3.12
Classifier: Operating System :: OS Independent
Requires-Python: >=3.10
License-File: LICENSE
Requires-Dist: croniter>=6.0.0
Requires-Dist: cyclopts>=3.16.1
Requires-Dist: deltalake>1.0.0
Requires-Dist: polars>=1.37.0
Requires-Dist: psutil>=7.0.0
Requires-Dist: typing-extensions>=4.14.1
Provides-Extra: azure
Requires-Dist: azure-identity>=1.17.0; extra == "azure"
Dynamic: license-file
